barcode_validator/__init__.py
barcode_validator/__main__.py
barcode_validator/_version.py
barcode_validator/cli.py
barcode_validator/constants.py
barcode_validator/criteria.py
barcode_validator/dna_analysis_result.py
barcode_validator/orchestrator.py
barcode_validator/config/__init__.py
barcode_validator/config/schema.yaml
barcode_validator/config/schema_config.py
barcode_validator/hmm_files/COI-5P.hmm
barcode_validator/hmm_files/__init__.py
barcode_validator/hmm_files/rbcL.hmm
barcode_validator/idservices/__init__.py
barcode_validator/idservices/blast.py
barcode_validator/idservices/bold.py
barcode_validator/idservices/bolddistilled.py
barcode_validator/idservices/factory.py
barcode_validator/idservices/galaxy_blast.py
barcode_validator/idservices/idservice.py
barcode_validator/resolvers/__init__.py
barcode_validator/resolvers/bold.py
barcode_validator/resolvers/bolddistilled.py
barcode_validator/resolvers/factory.py
barcode_validator/resolvers/ncbi.py
barcode_validator/resolvers/nsr.py
barcode_validator/resolvers/taxonomy.py
barcode_validator/validators/__init__.py
barcode_validator/validators/factory.py
barcode_validator/validators/non_coding.py
barcode_validator/validators/protein_coding.py
barcode_validator/validators/structural.py
barcode_validator/validators/taxonomic.py
barcode_validator/validators/validator.py
barcode_validator-2.0.10.dist-info/licenses/LICENSE.md
barcode_validator-2.0.10.dist-info/METADATA
barcode_validator-2.0.10.dist-info/WHEEL
barcode_validator-2.0.10.dist-info/top_level.txt
barcode_validator-2.0.10.dist-info/RECORD
