Metadata-Version: 2.4
Name: barcode_validator
Version: 2.0.10
Summary: A python package for structural and taxonomic validation of DNA barcode data.
Author-email: Rutger Vos <rutger.vos@naturalis.nl>
Requires-Python: >=3.9
License-File: LICENSE.md
Requires-Dist: nbitk>=0.6.2
Requires-Dist: biopython
Requires-Dist: requests
Requires-Dist: PyYAML
Dynamic: license-file
